editable_list_view/__init__.py
editable_list_view/editable_list_view.py
editable_list_view-1.0.0.dist-info/LICENSE.txt
editable_list_view-1.0.0.dist-info/METADATA
editable_list_view-1.0.0.dist-info/WHEEL
editable_list_view-1.0.0.dist-info/top_level.txt
editable_list_view-1.0.0.dist-info/RECORD
