Metadata-Version: 2.1
Name: editable-list-view
Version: 1.0.0
Summary: Editable list view for Django
Home-page: https://github.com/t-fujiki/editable_list_view
Author: Takaaki Fujiki
Author-email: 
License: UNKNOWN
Project-URL: Bug Tracker, https://github.com/t-fujiki/editable_list_view/issues
Platform: UNKNOWN
Classifier: Programming Language :: Python :: 3
Classifier: License :: OSI Approved :: MIT License
Classifier: Operating System :: OS Independent
Requires-Python: >=3.9
License-File: LICENSE.txt
